oxygen2/__init__.py
oxygen2/scripts.py
oxygen2/data/docs.txt
oxygen2-0.1.0.dist-info/METADATA
oxygen2-0.1.0.dist-info/WHEEL
oxygen2-0.1.0.dist-info/entry_points.txt
oxygen2-0.1.0.dist-info/top_level.txt
oxygen2-0.1.0.dist-info/RECORD
