Metadata-Version: 2.1
Name: oxygen2
Version: 0.1.0
Summary: GUI Development with Python, React and Typescript
Author-email: Esaú Mascarenhas <esaumasc@gmail.com>
License: MIT License
Project-URL: Homepage, https://github.com/EsauM10/oxygen2
Keywords: gui,eel,electron,typescript,javascript,react
Classifier: Development Status :: 3 - Alpha
Classifier: Programming Language :: Python :: 3.10
Classifier: Operating System :: OS Independent
Requires-Python: >=3.10
